hyperctui/__init__.py
hyperctui/__main__.py
hyperctui/_version.py
hyperctui/commands_launcher.py
hyperctui/event_handler.py
hyperctui/hyperctui.py
hyperctui/parent.py
hyperctui/autonomous_reconstruction/__init__.py
hyperctui/autonomous_reconstruction/event_handler.py
hyperctui/autonomous_reconstruction/get.py
hyperctui/autonomous_reconstruction/help_golden_angle.py
hyperctui/autonomous_reconstruction/initialization.py
hyperctui/autonomous_reconstruction/select_evaluation_regions.py
hyperctui/autonomous_reconstruction/select_tof_regions.py
hyperctui/crop/__init__.py
hyperctui/crop/crop.py
hyperctui/initialization/__init__.py
hyperctui/initialization/gui_initialization.py
hyperctui/log/__init__.py
hyperctui/log/log_launcher.py
hyperctui/pre_autonomous_monitor/__init__.py
hyperctui/pre_autonomous_monitor/event_handler.py
hyperctui/pre_autonomous_monitor/get.py
hyperctui/pre_autonomous_monitor/initialization.py
hyperctui/pre_autonomous_monitor/monitor.py
hyperctui/pre_processing_monitor/__init__.py
hyperctui/pre_processing_monitor/event_handler.py
hyperctui/pre_processing_monitor/get.py
hyperctui/pre_processing_monitor/initialization.py
hyperctui/pre_processing_monitor/monitor.py
hyperctui/preview_file/__init__.py
hyperctui/preview_file/preview_file_launcher.py
hyperctui/rotation_center/__init__.py
hyperctui/rotation_center/event_handler.py
hyperctui/rotation_center/rotation_center.py
hyperctui/session/__init__.py
hyperctui/session/load_previous_session_launcher.py
hyperctui/session/new_session.py
hyperctui/session/session_handler.py
hyperctui/setup_ob/__init__.py
hyperctui/setup_ob/event_handler.py
hyperctui/setup_ob/get.py
hyperctui/setup_projections/__init__.py
hyperctui/setup_projections/event_handler.py
hyperctui/setup_projections/get.py
hyperctui/static/VenusLogo.png
hyperctui/static/background_logo.png
hyperctui/static/golden_angle.csv
hyperctui/static/hyperctui_logo.png
hyperctui/static/more_infos.png
hyperctui/static/refresh.png
hyperctui-1.0.0.dist-info/licenses/LICENSE
hyperctui-1.0.0.dist-info/METADATA
hyperctui-1.0.0.dist-info/WHEEL
hyperctui-1.0.0.dist-info/entry_points.txt
hyperctui-1.0.0.dist-info/top_level.txt
hyperctui-1.0.0.dist-info/RECORD
