Metadata-Version: 2.4
Name: hyperctui
Version: 1.0.0
Summary: HyperCTui User Interface to run svmbir code with AI
Author-email: Jean Bilheux <bilheuxjm@ornl.gov>, "Venkatrishnan (Venkat) Singanallur" <venkatakrisv@ornl.gov>, Shimin Tang <tangs@ornl.gov>, Chen Zhang <zhangc@ornl.gov>
Maintainer-email: Jean Bilheux <bilheuxjm@ornl.gov>, Chen Zhang <zhangc@ornl.gov>
License: MIT
Project-URL: homepage, https://github.com/ornlneutronimaging/HyperCTui
Project-URL: repository, https://github.com/ornlneutronimaging/HyperCTui
Project-URL: issues, https://github.com/ornlneutronimaging/HyperCTui/issues
Keywords: HyperCTui,svmbir,AI,neutron
Classifier: Development Status :: 4 - Beta
Classifier: Programming Language :: Python :: 3
Classifier: License :: OSI Approved :: MIT License
Classifier: Topic :: Scientific/Engineering :: Physics
Classifier: Intended Audience :: Science/Research
Requires-Python: >=3.10
License-File: LICENSE
Requires-Dist: pandas
Requires-Dist: pillow
Requires-Dist: scikit-image
Requires-Dist: inflect
Requires-Dist: astropy
Requires-Dist: dxchange
Requires-Dist: h5py
Requires-Dist: QtPy
Requires-Dist: PyQt5
Requires-Dist: pyqtgraph
Requires-Dist: tqdm
Requires-Dist: loguru
Requires-Dist: neunorm
Requires-Dist: neutronbraggedge
Provides-Extra: dev
Requires-Dist: pytest>=7.0.0; extra == "dev"
Requires-Dist: pytest-cov; extra == "dev"
Requires-Dist: pre-commit; extra == "dev"
Requires-Dist: ruff; extra == "dev"
Provides-Extra: docs
Requires-Dist: sphinx>=8.2.1; extra == "docs"
Requires-Dist: sphinx_rtd_theme>=3.0.1; extra == "docs"
Provides-Extra: jupyter
Requires-Dist: jupyterlab; extra == "jupyter"
Requires-Dist: ipympl; extra == "jupyter"
Requires-Dist: ipywidgets; extra == "jupyter"
Provides-Extra: all
Requires-Dist: hyperctui[dev,docs,jupyter]; extra == "all"
Dynamic: license-file
